MANIFEST.in
README.rst
setup.py
data_chan/__init__.py
data_chan.egg-info/PKG-INFO
data_chan.egg-info/SOURCES.txt
data_chan.egg-info/dependency_links.txt
data_chan.egg-info/not-zip-safe
data_chan.egg-info/top_level.txt
data_chan/instruments/__init__.py
data_chan/instruments/fermiumlabs_labtrek_jv/__init__.py
data_chan/instruments/fermiumlabs_labtrek_jv/hall_effect_apparatus.py
data_chan/lib/libDataChan.dll
data_chan/lib/libDataChan.dylib
data_chan/lib/libDataChan.so