Metadata-Version: 1.1
Name: data-chan
Version: 0.2.1
Summary: Python bindings for Data-Chan
Home-page: https://github.com/fermiumlabs/data-chan-python/
Author: Fermium LABS
Author-email: info@fermiumlabs.com
License: Apache 2
Platform: UNKNOWN
Classifier: Development Status :: 3 - Alpha
Classifier: Intended Audience :: Developers
Classifier: Intended Audience :: Science/Research
Classifier: License :: OSI Approved :: Apache Software License
Classifier: Programming Language :: Python :: 3
Classifier: Operating System :: Microsoft :: Windows
Classifier: Operating System :: MacOS
Classifier: Operating System :: POSIX :: Linux
Classifier: Operating System :: Unix
